winauth/__init__.py
winauth/__main__.py
pywinauth-0.4.0.dist-info/LICENSE
pywinauth-0.4.0.dist-info/METADATA
pywinauth-0.4.0.dist-info/WHEEL
pywinauth-0.4.0.dist-info/entry_points.txt
pywinauth-0.4.0.dist-info/top_level.txt
pywinauth-0.4.0.dist-info/zip-safe
pywinauth-0.4.0.dist-info/RECORD
