Metadata-Version: 2.1
Name: pywinauth
Version: 0.4.0
Summary: A tool to generate TOTP code based using secrets from WinAuth
Home-page: https://github.com/zeevro/pywinauth
Author: Zeev Rotshtein
Author-email: zeevro@gmail.com
Maintainer: Zeev Rotshtein
Maintainer-email: zeevro@gmail.com
License: UNKNOWN
Download-URL: https://github.com/zeevro/pywinauth/archive/master.zip
Keywords: WinAuth,TOTP,2FA,MFA
Platform: UNKNOWN
Classifier: Development Status :: 4 - Beta
Classifier: Environment :: Console
Classifier: License :: Public Domain
Classifier: Natural Language :: English
Classifier: Programming Language :: Python :: 3
Classifier: Operating System :: Microsoft :: Windows
Classifier: Topic :: Security
Classifier: Topic :: Utilities
Classifier: Typing :: Typed
License-File: LICENSE
Requires-Dist: xmltodict
Requires-Dist: pyotp
Requires-Dist: pyperclip
Requires-Dist: fuzzywuzzy
Requires-Dist: qrcode
